blockcard/__init__.py
blockcard/__main__.py
blockcard/block.py
blockcard-0.1.2.dist-info/LICENSE
blockcard-0.1.2.dist-info/METADATA
blockcard-0.1.2.dist-info/WHEEL
blockcard-0.1.2.dist-info/top_level.txt
blockcard-0.1.2.dist-info/RECORD
