Metadata-Version: 2.1
Name: blockcard
Version: 0.1.2
Summary: It's the proof-of-thought that counts
Home-page: https://github.com/ckw017/blockcard
Author: Chris K. W.
Author-email: chriskw.xyz@gmail.com
License: MIT
Platform: UNKNOWN
Classifier: Development Status :: 4 - Beta
Classifier: License :: OSI Approved :: MIT License
Classifier: Intended Audience :: Developers
Classifier: Programming Language :: Python :: 3
Classifier: Operating System :: OS Independent
Classifier: Natural Language :: English
Requires-Dist: colorama
Requires-Dist: pytz
Requires-Dist: dateutils
